mycalc/calculator.py
sejinchun0411-0.0.1.dist-info/METADATA
sejinchun0411-0.0.1.dist-info/WHEEL
sejinchun0411-0.0.1.dist-info/top_level.txt
sejinchun0411-0.0.1.dist-info/RECORD
