Metadata-Version: 2.1
Name: sejinchun0411
Version: 0.0.1
Summary: my calculator
Home-page: https://github.com/chunsejin/mycalc
Download-URL: https://github.com/chunsejin/mycalc/mycalc.zip
Author: sejin chun
License: UNKNOWN
Platform: UNKNOWN
Classifier: Programming Language :: Python :: 3
